codex_oauth/__init__.py
codex_oauth/auth.py
codex_oauth/client.py
codex_oauth/env.py
codex_oauth/exceptions.py
codex_oauth/instructions.py
codex_oauth/models.py
codex_oauth/response.py
codex_oauth/sse.py
codex_oauth/store.py
codex_oauth/bundled_prompts/__init__.py
codex_oauth/bundled_prompts/gpt-5.2-codex-instructions.md
langchain_codex_oauth/__init__.py
langchain_codex_oauth/chat_models.py
langchain_codex_oauth/cli.py
langchain_codex_oauth/tooling.py
langchain_codex_oauth/version.py
langchain_codex_oauth-1.0.0.dist-info/METADATA
langchain_codex_oauth-1.0.0.dist-info/WHEEL
langchain_codex_oauth-1.0.0.dist-info/entry_points.txt
langchain_codex_oauth-1.0.0.dist-info/top_level.txt
langchain_codex_oauth-1.0.0.dist-info/RECORD
