Metadata-Version: 2.4
Name: langchain-codex-oauth
Version: 1.0.0
Summary: Use ChatGPT Plus/Pro Codex (OAuth) as a LangChain/LangGraph chat model
License-Expression: MIT
Keywords: langchain,langgraph,codex,chatgpt,oauth
Requires-Python: >=3.10
Requires-Dist: httpx>=0.27.0
Requires-Dist: langchain-core>=1.0.0
Provides-Extra: dev
Requires-Dist: pytest>=8.0.0; extra == "dev"
Requires-Dist: ruff>=0.6.0; extra == "dev"
